pyi18next/__init__.py
pyi18next/backends/__init__.py
pyi18next/backends/fs.py
pyi18next/i18next.py
pyi18next/loaders/__init__.py
pyi18next/translate.py
pyi18next/utility.py
pyi18next-0.0.2.dist-info/LICENSE
pyi18next-0.0.2.dist-info/METADATA
pyi18next-0.0.2.dist-info/WHEEL
pyi18next-0.0.2.dist-info/RECORD
