Metadata-Version: 2.1
Name: pyi18next
Version: 0.0.2
Summary: A Python implementation of i18next.
Home-page: https://github.com/gzttech/pyi18next
License: MIT
Author: Gongziting Tech Ltd.
Requires-Python: >=3.7,<4.0
Classifier: License :: OSI Approved :: MIT License
Classifier: Programming Language :: Python :: 3
Classifier: Programming Language :: Python :: 3.7
Classifier: Programming Language :: Python :: 3.8
Classifier: Programming Language :: Python :: 3.9
Classifier: Programming Language :: Python :: 3.10
Classifier: Programming Language :: Python :: 3.11
Classifier: Programming Language :: Python :: 3.12
Requires-Dist: babel (>=2.14.0,<3.0.0)
